MANIFEST.in
README.rst
setup.cfg
setup.py
CopyleaksPythonSDK.egg-info/PKG-INFO
CopyleaksPythonSDK.egg-info/SOURCES.txt
CopyleaksPythonSDK.egg-info/dependency_links.txt
CopyleaksPythonSDK.egg-info/requires.txt
CopyleaksPythonSDK.egg-info/top_level.txt
copyleaks_sdk/__init__.py
copyleaks_sdk/copyleaks.py