Metadata-Version: 1.1
Name: CopyleaksPythonSDK
Version: 0.1
Summary: A Python SDK for Copyleaks (http://copyleaks.com)
Home-page: https://github.com/wyounas/copyleaks-python-sdk
Author: Waqas Younas
Author-email: waqas.younas@gmail.com
License: UNKNOWN
Keywords: copyleaks,copyleakssdk,sdk
Platform: UNKNOWN
Classifier: Development Status :: 3 - Alpha
Classifier: Intended Audience :: Developers
Classifier: Topic :: Internet
Classifier: Topic :: Software Development :: Libraries
Classifier: Topic :: Software Development :: Libraries :: Python Modules
Classifier: Programming Language :: Python :: 2.7
